compas_rui/__init__.py
compas_rui/callbacks.py
compas_rui/feedback.py
compas_rui/mouse.py
compas_rui/rui.py
compas_rui/forms/__init__.py
compas_rui/forms/about.py
compas_rui/forms/error.py
compas_rui/forms/filesystem.py
compas_rui/forms/info.py
compas_rui/forms/meshdata.py
compas_rui/forms/meshinfo.py
compas_rui/forms/namedvalues.py
compas_rui/forms/scene.py
compas_rui/forms/settings.py
compas_rui/forms/splash.py
compas_rui/scene/__init__.py
compas_rui/scene/meshobject.py
compas_rui/values/__init__.py
compas_rui/values/boolvalue.py
compas_rui/values/colorvalue.py
compas_rui/values/dictvalue.py
compas_rui/values/listvalue.py
compas_rui/values/numbervalue.py
compas_rui/values/settings.py
compas_rui/values/strvalue.py
compas_rui/values/value.py
compas_rui-0.6.0.dist-info/licenses/LICENSE
compas_rui-0.6.0.dist-info/METADATA
compas_rui-0.6.0.dist-info/WHEEL
compas_rui-0.6.0.dist-info/top_level.txt
compas_rui-0.6.0.dist-info/RECORD
